rcdesign/__about__.py
rcdesign/__init__.py
rcdesign/__main__.py
rcdesign/brent.py
rcdesign/main.py
rcdesign/utils.py
rcdesign/is456/__init__.py
rcdesign/is456/concrete.py
rcdesign/is456/constants.py
rcdesign/is456/design.py
rcdesign/is456/detailing.py
rcdesign/is456/rebar.py
rcdesign/is456/section.py
rcdesign/is456/stressblock.py
rcdesign-0.4.18.dist-info/METADATA
rcdesign-0.4.18.dist-info/WHEEL
rcdesign-0.4.18.dist-info/entry_points.txt
rcdesign-0.4.18.dist-info/licenses/LICENSE.md
rcdesign-0.4.18.dist-info/RECORD
