Metadata-Version: 2.4
Name: rcdesign
Version: 0.4.18
Summary: A Python package for reinforced concrete analysis and design as per IS 456:2000
Project-URL: Documentation, https://github.com/satish-annigeri/rcdesign#readme
Project-URL: Issues, https://github.com/satish-annigeri/rcdesign/issues
Project-URL: Source, https://github.com/satish-annigeri/rcdesign
Project-URL: Home, https://github.com/satish-annigeri/rcdesign
Author-email: Satish Annigeri <satish.annigeri@gmail.com>
License: MIT License
License-File: LICENSE.md
Classifier: Development Status :: 4 - Beta
Classifier: Intended Audience :: Developers
Classifier: License :: OSI Approved :: MIT License
Classifier: Operating System :: OS Independent
Classifier: Programming Language :: Python
Classifier: Programming Language :: Python :: 3.7
Classifier: Programming Language :: Python :: 3.8
Classifier: Programming Language :: Python :: 3.9
Classifier: Programming Language :: Python :: 3.10
Classifier: Programming Language :: Python :: 3.11
Classifier: Programming Language :: Python :: Implementation :: CPython
Classifier: Programming Language :: Python :: Implementation :: PyPy
Classifier: Topic :: Scientific/Engineering
Classifier: Topic :: Software Development :: Libraries :: Python Modules
Requires-Python: >=3.12
Requires-Dist: numpy>=2.2.5
Requires-Dist: scipy>=1.15.3
Requires-Dist: sympy>=1.14.0
